FFD.v
//caso FF tipo D sin set ni reset
module FF_D(
    input wire D,
    input wire clk,
    output reg Q = 0,
    output wire Qn
);
    always @(posedge clk) begin
        Q <= D;
    end
    assign Qn = ~Q;
endmodule

Contador.v
module contador_ascendente_descendente(
    input wire clk,
    input wire r,
    input wire s,
    output wire [2:0] leds
);

wire D2, D1, D0;
wire Q2, Q1, Q0;

// Lógica para las entradas D de los flip-flops tipo D
assign D2 = (~r & Q2) | (~s & Q2 & Q0) | (~s & Q2 & Q1) | (s & ~r & Q1 & Q0);
assign D1 = (~r & Q1 & ~Q0) | (~s & Q1 & Q0) | (~s & r & Q2 & ~Q1 & ~Q0) | 
            (s & ~r & ~Q1 & Q0) | (s & ~r & Q2 & Q0);
assign D0 = (~s & ~r & Q0) | (~s & r & Q1 & ~Q0) | (~s & r & Q2 & ~Q0) | 
            (s & ~r & Q2 & Q1) | (s & ~r & ~Q0);

FF_D ffd_2(
    .D(D2),
    .clk(clk),
    .Q(Q2)
);
FF_D ffd_1(
    .D(D1),
    .clk(clk),
    .Q(Q1)
);
FF_D ffd_0(
    .D(D0),
    .clk(clk),
    .Q(Q0)
);     

assign leds = {Q2, Q1, Q0};



endmodule

TFI_tb.v
`timescale 1ns/1ps

module TFI_tb();

// Entradas
reg clk = 0;
reg r = 0;
reg s = 0;

// Salidas
wire [2:0] leds;

contador_ascendente_descendente UUT(
    .clk(clk),
    .r(r),
    .s(s),
    .leds(leds)
);

always #1 clk = ~clk;

initial begin
  $dumpfile("TFI_tb.vcd");
  $dumpvars(0, TFI_tb);
  // Generación del reloj
  #5;
  s = 1;
  #5;
  s = 0;
  #5;
  s = 1;
  #5;
  s = 0;
  #5;
  s = 1;
  #5;
  s = 0;
  #5;
  s = 1;
  #5;
  s = 0;
  #5;
  s = 1;
  #5;
  s = 0;
  #5;
  s = 1;
  #5;
  s = 0;
  #5;
  s = 1;
  #5;
  s = 0;
  #5;
  r = 1;
  #5;
  r = 0;
  #5;
  r = 1;
  #5;
  r = 0;
  #5;
  r = 1;
  #5;
  r = 0;
  #5;
  r = 1;
  #5;
  r = 0;
  #5;
  r = 1;
  #5;
  r = 0;
  #5;
  r = 1;
  #5;
  r = 0;
  #5;
  r = 1;
  #5;
  r = 0;
  #5;
  r = 1;
  #5;
  r = 0;
  $finish;
end

endmodule

TFI_tb.vcd
$date
	Fri Jun 20 14:05:27 2025
$end
$version
	Icarus Verilog
$end
$timescale
	1ps
$end
$scope module TFI_tb $end
$var wire 3 ! leds [2:0] $end
$var reg 1 " clk $end
$var reg 1 # r $end
$var reg 1 $ s $end
$scope module UUT $end
$var wire 1 % D0 $end
$var wire 1 & D1 $end
$var wire 1 ' D2 $end
$var wire 1 " clk $end
$var wire 1 # r $end
$var wire 1 $ s $end
$var wire 3 ( leds [2:0] $end
$var wire 1 ) Q2 $end
$var wire 1 * Q1 $end
$var wire 1 + Q0 $end
$scope module ffd_0 $end
$var wire 1 % D $end
$var wire 1 , Qn $end
$var wire 1 " clk $end
$var reg 1 + Q $end
$upscope $end
$scope module ffd_1 $end
$var wire 1 & D $end
$var wire 1 - Qn $end
$var wire 1 " clk $end
$var reg 1 * Q $end
$upscope $end
$scope module ffd_2 $end
$var wire 1 ' D $end
$var wire 1 . Qn $end
$var wire 1 " clk $end
$var reg 1 ) Q $end
$upscope $end
$upscope $end
$upscope $end
$enddefinitions $end
$comment Show the parameter values. $end
$dumpall
$end
#0
$dumpvars
1.
1-
1,
0+
0*
0)
b0 (
0'
0&
0%
0$
0#
0"
b0 !
$end
#1000
1"
#2000
0"
#3000
1"
#4000
0"
#5000
1%
1"
1$
#6000
0"
#7000
0%
1&
0,
b1 !
b1 (
1+
1"
#8000
0"
#9000
1%
1&
0-
1,
1*
b10 !
b10 (
0+
1"
#10000
0%
0"
0$
#11000
1"
#12000
0"
#13000
1"
#14000
0"
#15000
1%
1"
1$
#16000
0"
#17000
0&
0%
1'
0,
b11 !
b11 (
1+
1"
#18000
0"
#19000
1%
1'
1,
1-
0.
0+
0*
b100 !
b100 (
1)
1"
#20000
0%
0"
0$
#21000
1"
#22000
0"
#23000
1"
#24000
0"
#25000
1%
1"
1$
#26000
0"
#27000
0%
1&
0,
b101 !
b101 (
1+
1"
#28000
0"
#29000
1%
1&
0-
1,
1*
b110 !
b110 (
0+
1"
#30000
0%
0"
0$
#31000
1"
#32000
0"
#33000
1"
#34000
0"
#35000
1%
1"
1$
#36000
0"
#37000
0,
b111 !
b111 (
1+
1"
#38000
0"
#39000
1"
#40000
1%
1&
0"
0$
#41000
1"
#42000
0"
#43000
1"
#44000
0"
#45000
1"
1$
#46000
0"
#47000
1"
#48000
0"
#49000
1"
#50000
1%
1&
0"
0$
#51000
1"
#52000
0"
#53000
1"
#54000
0"
#55000
1"
1$
#56000
0"
#57000
1"
#58000
0"
#59000
1"
#60000
1%
1&
0"
0$
#61000
1"
#62000
0"
#63000
1"
#64000
0"
#65000
1"
1$
#66000
0"
#67000
1"
#68000
0"
#69000
1"
#70000
1%
1&
0"
0$
#71000
1"
#72000
0"
#73000
1"
#74000
0"
#75000
0%
1"
1#
#76000
0"
#77000
1%
0&
1,
b110 !
b110 (
0+
1"
#78000
0"
#79000
0%
1'
0,
1-
1+
b101 !
b101 (
0*
1"
#80000
1%
0"
0#
#81000
1"
#82000
0"
#83000
1"
#84000
0"
#85000
0%
1"
1#
#86000
0"
#87000
1%
1&
0'
1,
b100 !
b100 (
0+
1"
#88000
0"
#89000
0%
1&
0'
1.
0-
0,
0)
1*
b11 !
b11 (
1+
1"
#90000
1%
0"
0#
#91000
1"
#92000
0"
#93000
1"
#94000
0"
#95000
0%
1"
1#
#96000
0"
#97000
1%
0&
1,
b10 !
b10 (
0+
1"
#98000
0"
#99000
0%
0,
1-
1+
b1 !
b1 (
0*
1"
#100000
1%
0"
0#
#101000
1"
#102000
0"
#103000
1"
#104000
0"
#105000
0%
1"
1#
#106000
0"
#107000
1,
b0 !
b0 (
0+
1"
#108000
0"
#109000
1"
#110000
0"
0#
#111000
1"
#112000
0"
#113000
1"
#114000
0"
#115000
1"
1#
#116000
0"
#117000
1"
#118000
0"
#119000
1"
#120000
0"
0#
#121000
1"
#122000
0"
#123000
1"
#124000
0"
#125000
1"
1#
#126000
0"
#127000
1"
#128000
0"
#129000
1"
#130000
0"
0#
#131000
1"
#132000
0"
#133000
1"
#134000
0"
#135000
1"
1#
#136000
0"
#137000
1"
#138000
0"
#139000
1"
#140000
0"
0#
#141000
1"
#142000
0"
#143000
1"
#144000
0"
#145000
1"
1#
#146000
0"
#147000
1"
#148000
0"
#149000
1"
#150000
0"
0#
