Codigo/FFD.v
// Flip-Flop D activado por flanco de subida 
module FF_D(
    input wire D,
    input wire clk,
    output reg Q = 0,
    output wire Qn
);
    always @(posedge clk) begin
        Q <= D;
    end
    assign Qn = ~Q;
endmodule

Codigo/Contador.v
// Contador ascendente y descendente de 3 bits con flip-flops tipo D
module contador_ascendente_descendente(
    input wire clk, // Reloj
    input wire r, // Entrada que representa la salida de un auto del estacionamiento
    input wire s, // Entrada que representa el ingreso de un auto al estacionamiento
    output wire [2:0] leds // Salida de 3 bits que indica el estado del contador
);

    // Entradas para los flip-flops tipo D
    wire D2, D1, D0;

    // Salidas de los flip-flops tipo D
    wire Q2, Q1, Q0;

    // Implementación de la lógica combinacional para las entradas D de los flip-flops
    assign D2 = (~r & Q2) | (~s & Q2 & Q0) | (~s & Q2 & Q1) | (s & ~r & Q1 & Q0);
    assign D1 = (~r & Q1 & ~Q0) | (~s & Q1 & Q0) | (~s & r & Q2 & ~Q1 & ~Q0) | 
                (s & ~r & ~Q1 & Q0) | (s & ~r & Q2 & Q0);
    assign D0 = (~s & ~r & Q0) | (~s & r & Q1 & ~Q0) | (~s & r & Q2 & ~Q0) | 
                (s & ~r & Q2 & Q1) | (s & ~r & ~Q0);

    // Instanciación de los flip-flops tipo D
    FF_D ffd_2(.D(D2), .clk(clk), .Q(Q2), .Qn());
    FF_D ffd_1(.D(D1), .clk(clk), .Q(Q1), .Qn());
    FF_D ffd_0(.D(D0), .clk(clk), .Q(Q0), .Qn());     

    // Asignación de las salidas del contador a el registro que representa los LEDs
    // que indican el estado del estacionamiento
    assign leds = {Q2, Q1, Q0};

endmodule

Codigo/FSM_control_estacionamiento.v
// Módulo de una máquina de estados finitos (FSM) que controla la entrada y salida de autos en un estacionamiento.
module FSM_control_estacionamiento(
    input wire clk, // Reloj
    input wire a, // Entrada que representa al 1er sensor del estacionamiento
    input wire b, // Entrada que representa al 2do sensor del estacionamiento
    output wire S, // Salida que representa el ingreso de un auto al estacionamiento
    output wire R // Salida que represeta la salida de un auto del estacionamiento
);
   
    // Entradas para los flip-flops tipo D
    wire D2, D1, D0;

     // Salidas de los flip-flops tipo D
    wire Q2, Q1, Q0;

    // Implementación de la lógica combinacional para las entradas D de los flip-flops
    assign D2 = (b & Q2 & ~Q1) | (~a & b & ~Q1 & ~Q0) |
                (a & Q2 & Q1 & ~Q0) | (a & Q2 & ~Q1 & Q0);

    assign D1 = (b & ~Q2 & Q1) | (a & b & ~Q2 & Q0) |
                (a & ~b & Q2 & ~Q1 & Q0) | (a & ~b & Q2 & Q1 & ~Q0);

    assign D0 = (~a & b & ~Q2 & Q1) | (a & ~b & ~Q2 & ~Q1) | 
                (a & b & Q2 & ~Q1) | (a & ~b & ~Q2 & ~Q0) |
                (a & b & Q2 & ~Q0);
 
    // Instanciación de los flip-flops tipo D
    FF_D ff2 (.D(D2), .clk(clk), .Q(Q2), .Qn());
    FF_D ff1 (.D(D1), .clk(clk), .Q(Q1), .Qn());
    FF_D ff0 (.D(D0), .clk(clk), .Q(Q0), .Qn());

    // Asignación de las salidas S y R (ingreso y salida de autos)
    assign S = ~a & ~b & ~Q2 & Q1 & Q0;
    assign R = ~a & ~b & Q2 & Q1 & ~Q0;

endmodule

Codigo/antirebote.v
// Descripción: Módulo para eliminar el rebote de un botón
module antirebote( 
  input wire BTN, // Entrada del botón que se desea estabilizar
  input wire clk, // Reloj del sistema
  output wire BTN_estable // Salida del botón estabilizado  
);

  // Registros para almacenar los valores intermedios
  reg btn_aux1 = 1'b0; // Guarda el valor más reciente del botón
  reg btn_aux2 = 1'b0; // Guarda el valor estabilizado del botón

  /*
  Este contador de 17 bits se utiliza para esperar cierto tiempo antes de considerar que 
  la señal del botón es estable. La idea es: si BTN no cambia durante un tiempo suficientemente 
  largo (por ejemplo, unos milisegundos), entonces se considera que el valor actual es confiable.
  */
  reg [16:0] contador = 0; // Contador para el tiempo de estabilización

  always @(posedge clk) begin 

    if (btn_aux1 ^ BTN == 1'b1) 
      begin
        // Si hay un cambio en el botón, reiniciar el contador
        contador <= 0;
        btn_aux1 <= BTN; // Actualizar al valor mas reciente del botón
      end
    else if (contador[16] == 1'b0) // Se espera que el bit más alto del contador (contador[16]) llegue a 1, lo cual indica que ha pasado suficiente tiempo sin cambios.
      contador <= contador + 1; // Incrementar el contador si no hay cambio
    else
      btn_aux2 <= btn_aux1; // Si el contador ha llegado al final, actualizar la salida estable

  end

  assign BTN_estable = btn_aux2; // Asignar el valor del segundo registro auxiliar a la salida estable

endmodule

Codigo/TFI.v
/* 
 Modulo TFI (Trabajo Final Integrador)
 Descripcion: Este modulo implementa un sistema de control de estacionamiento
 utilizando una maquina de estados finitos (FSM) que controla la entrada y salida de autos,
 un contador ascendente/descendente para llevar el registro de autos en el estacionamiento,
 y un debouncer para estabilizar las entradas de los sensores.

 Universidad Nacional del Litoral
 Facultad de Ingenieria y Ciencias Hídricas
 -Materia: Electronica Digital
 -Profesores: Padula Eugenio, Quiroga Alejandro, Sanchez Guido
 -Autores: Godoy Matias, Palacios Angel
 -Fecha: 2025-06-23
*/

module TFI(
  input CLK, // Reloj de la edu-ciaa-fpga
  input BTN1, // Entrada que repesenta al par de sensores 'a' del estacionamiento
  input BTN4, // Entrada que repreesnta al par de sensores 'b' del estacionamiento
  // Salidas para los LEDs que indican el estado del estacionamiento
  output wire LED3,
  output wire LED2, 
  output wire LED1,
  output wire LED0
);

  wire BTN1_estable; // Botón 1 estabilizado (sensor a)
  // Instanciación del módulo debouncer para estabilizar la señal del botón 1
  antirebote antirebote_boton1( 
    .BTN(~BTN1),
    .clk(CLK),
    .BTN_estable(BTN1_estable)
  );

  wire BTN4_estable; // Botón 4 estabilizado (sensor b)
  // Instanciación del módulo debouncer para estabilizar la señal del botón 4
  antirebote antirebote_boton4(
    .BTN(~BTN4),
    .clk(CLK),
    .BTN_estable(BTN4_estable)
  );

  wire s; // Señal de entrada para el contador ascendente/descendente (ingreso de auto)
  wire r; // Señal de salida para el contador ascendente/descendente (salida de auto)

  // Instanciación de la máquina de estados finitos (FSM) que controla la entrada y salida de autos
  FSM_control_estacionamiento fsm(
    .clk(CLK),
    .a(BTN1_debounced),
    .b(BTN4_debounced),
    .S(s),
    .R(r)
  );

  wire [2:0] leds; // Salidas del contador ascendente/descendente que indican el estado del estacionamiento

  // Instanciación del contador ascendente/descendente que lleva el registro de autos en el estacionamiento
  contador_ascendente_descendente contador(
    .clk(CLK),
    .r(r),
    .s(s),
    .leds(leds)
  );
  
  // Asignación de los LEDs a las salidas del contador
  assign LED3 = 1'b0; // LED3 siempre apagado
  assign LED2 = leds[2];
  assign LED1 = leds[1];
  assign LED0 = leds[0];

endmodule

Codigo/TFI_tb.v
`timescale 1ns/1ps

module TFI_tb();

  // Entradas
  reg clk = 0; // Reloj de la edu-ciaa-fpga
  reg a = 0; // Entrada que representa al par de sensores 'a' del estacionamiento
  reg b = 0; // Entrada que representa al par de sensores 'b' del estacionamiento

  // Salidas
  wire LED_3; // LED que indica el estado del estacionamiento (siempre apagado)
  wire LED_2; // LED que indica el estado del estacionamiento
  wire LED_1; // LED que indica el estado del estacionamiento
  wire LED_0; // LED que indica el estado del estacionamiento

  TFI UUT(
    .CLK(clk), // Conexión del reloj
    .BTN1(a), // Conexión del primer botón (sensor 'a')
    .BTN4(b), // Conexión del segundo botón (sensor 'b')
    .LED3(LED_3), // Conexión del LED 3
    .LED2(LED_2), // Conexión del LED 2
    .LED1(LED_1), // Conexión del LED 1
    .LED0(LED_0)  // Conexión del LED 0
  );

  always #1 clk = ~clk;

  initial begin
    $dumpfile("TFI_tb.vcd");
    $dumpvars(0, TFI_tb);
    #10; // Espera 10 unidades de tiempo para iniciar la simulación
    // Simulación de la entrada de autos al estacionamiento
    a = 1; // Simula la activación del sensor 'a'
    b = 0; // Sensor 'b' inactivo
    #10; // Espera 10 unidades de tiempo
    a = 1; // Mantiene el sensor 'a' activo
    b = 1; // Activa el sensor 'b'
    #10; // Espera 10 unidades de tiempo
    a = 0; // Desactiva el sensor 'a'
    b = 1; // Mantiene el sensor 'b' activo
    #10; // Espera 10 unidades de tiempo
    a = 0; // Desactiva el sensor 'a'
    b = 0; // Desactiva el sensor 'b'
    #10; // Espera 10 unidades de tiempo

    $finish;
  end

endmodule

Codigo/TFI_tb.vcd
$date
	Sat Jun 21 18:41:49 2025
$end
$version
	Icarus Verilog
$end
$timescale
	1ps
$end
$scope module TFI_tb $end
$var wire 1 ! LED_3 $end
$var wire 1 " LED_2 $end
$var wire 1 # LED_1 $end
$var wire 1 $ LED_0 $end
$var reg 1 % a $end
$var reg 1 & b $end
$var reg 1 ' clk $end
$scope module UUT $end
$var wire 1 % BTN1 $end
$var wire 1 ( BTN1_debounced $end
$var wire 1 & BTN4 $end
$var wire 1 ) BTN4_debounced $end
$var wire 1 ' CLK $end
$var wire 1 ! LED3 $end
$var wire 1 * s $end
$var wire 1 + r $end
$var wire 3 , leds [2:0] $end
$var wire 1 " LED2 $end
$var wire 1 # LED1 $end
$var wire 1 $ LED0 $end
$var wire 1 - BTN4_estable $end
$var wire 1 . BTN1_estable $end
$scope module antirebote_boton1 $end
$var wire 1 / BTN $end
$var wire 1 . BTN_estable $end
$var wire 1 ' clk $end
$var reg 1 0 btn_aux1 $end
$var reg 1 1 btn_aux2 $end
$var reg 17 2 contador [16:0] $end
$upscope $end
$scope module antirebote_boton4 $end
$var wire 1 3 BTN $end
$var wire 1 - BTN_estable $end
$var wire 1 ' clk $end
$var reg 1 4 btn_aux1 $end
$var reg 1 5 btn_aux2 $end
$var reg 17 6 contador [16:0] $end
$upscope $end
$scope module contador $end
$var wire 1 7 D0 $end
$var wire 1 8 D1 $end
$var wire 1 9 D2 $end
$var wire 1 ' clk $end
$var wire 1 * s $end
$var wire 1 + r $end
$var wire 3 : leds [2:0] $end
$var wire 1 ; Q2 $end
$var wire 1 < Q1 $end
$var wire 1 = Q0 $end
$scope module ffd_0 $end
$var wire 1 7 D $end
$var wire 1 > Qn $end
$var wire 1 ' clk $end
$var reg 1 = Q $end
$upscope $end
$scope module ffd_1 $end
$var wire 1 8 D $end
$var wire 1 ? Qn $end
$var wire 1 ' clk $end
$var reg 1 < Q $end
$upscope $end
$scope module ffd_2 $end
$var wire 1 9 D $end
$var wire 1 @ Qn $end
$var wire 1 ' clk $end
$var reg 1 ; Q $end
$upscope $end
$upscope $end
$scope module fsm $end
$var wire 1 A D0 $end
$var wire 1 B D1 $end
$var wire 1 C D2 $end
$var wire 1 + R $end
$var wire 1 * S $end
$var wire 1 ( a $end
$var wire 1 ) b $end
$var wire 1 ' clk $end
$var wire 1 D Q2 $end
$var wire 1 E Q1 $end
$var wire 1 F Q0 $end
$scope module ff0 $end
$var wire 1 A D $end
$var wire 1 G Qn $end
$var wire 1 ' clk $end
$var reg 1 F Q $end
$upscope $end
$scope module ff1 $end
$var wire 1 B D $end
$var wire 1 H Qn $end
$var wire 1 ' clk $end
$var reg 1 E Q $end
$upscope $end
$scope module ff2 $end
$var wire 1 C D $end
$var wire 1 I Qn $end
$var wire 1 ' clk $end
$var reg 1 D Q $end
$upscope $end
$upscope $end
$upscope $end
$upscope $end
$enddefinitions $end
$comment Show the parameter values. $end
$dumpall
$end
#0
$dumpvars
1I
1H
1G
0F
0E
0D
xC
0B
xA
1@
1?
1>
0=
0<
0;
b0 :
09
08
07
b0 6
05
04
13
b0 2
01
00
1/
0.
0-
b0 ,
0+
0*
z)
z(
0'
0&
0%
0$
0#
0"
0!
$end
#1000
xB
xI
xG
10
14
xD
xF
1'
#2000
0'
#3000
x7
x+
x*
xH
xE
b1 6
b1 2
1'
#4000
0'
#5000
x8
x>
x$
b10 2
b10 6
b0x ,
b0x :
x=
1'
#6000
0'
#7000
x9
x?
x#
b0xx ,
b0xx :
x<
b11 6
b11 2
1'
#8000
0'
#9000
x@
x"
b100 2
b100 6
bx ,
bx :
x;
1'
#10000
0/
0'
1%
#11000
b101 6
00
b0 2
1'
#12000
0'
#13000
b1 2
b110 6
1'
#14000
0'
#15000
b111 6
b10 2
1'
#16000
0'
#17000
b11 2
b1000 6
1'
#18000
0'
#19000
b1001 6
b100 2
1'
#20000
03
0'
1&
#21000
b101 2
04
b0 6
1'
#22000
0'
#23000
b1 6
b110 2
1'
#24000
0'
#25000
b111 2
b10 6
1'
#26000
0'
#27000
b11 6
b1000 2
1'
#28000
0'
#29000
b1001 2
b100 6
1'
#30000
1/
0'
0%
#31000
b101 6
10
b0 2
1'
#32000
0'
#33000
b1 2
b110 6
1'
#34000
0'
#35000
b111 6
b10 2
1'
#36000
0'
#37000
b11 2
b1000 6
1'
#38000
0'
#39000
b1001 6
b100 2
1'
#40000
13
0'
0&
#41000
b101 2
14
b0 6
1'
#42000
0'
#43000
b1 6
b110 2
1'
#44000
0'
#45000
b111 2
b10 6
1'
#46000
0'
#47000
b11 6
b1000 2
1'
#48000
0'
#49000
b1001 2
b100 6
1'
